TamilLexicheck/TamilLexicheck.py
TamilLexicheck/__init__.py
TamilLexicheck/words.pickle
TamilLexicheck-1.0.12.dist-info/METADATA
TamilLexicheck-1.0.12.dist-info/WHEEL
TamilLexicheck-1.0.12.dist-info/top_level.txt
TamilLexicheck-1.0.12.dist-info/RECORD
