Metadata-Version: 2.1
Name: TamilLexicheck
Version: 1.0.12
Summary: Tamil Lexicheck is an open-source project aimed at providing a tool for identifying and suggesting corrections for misspelled words in Tamil text. This project is licensed under the Apache License 2.0.
Home-page: https://github.com/Raam-kishore/TamilLexicheck-public-.git
Author: raamkishore
Author-email: raamkishore@megalai.com
License: UNKNOWN
Platform: UNKNOWN
Classifier: Programming Language :: Python :: 3
Classifier: License :: OSI Approved :: MIT License
Classifier: Operating System :: OS Independent
Requires-Python: >=3.6
